rustivig-0.4.2.dist-info/METADATA
rustivig-0.4.2.dist-info/WHEEL
rustivig-0.4.2.dist-info/licenses/LICENSE
rustivig/__init__.py
rustivig/__init__.pyi
rustivig/py.typed
rustivig/rustivig.cpython-313-powerpc64le-linux-gnu.so
rustivig-0.4.2.dist-info/RECORD
