Metadata-Version: 2.4
Name: rustivig
Version: 0.4.2
Classifier: Programming Language :: Rust
Classifier: Programming Language :: Python :: Implementation :: CPython
Classifier: Programming Language :: Python :: Implementation :: PyPy
Requires-Dist: ruff ; extra == 'dev'
Requires-Dist: pytest ; extra == 'dev'
Requires-Dist: pyspellchecker ; extra == 'dev'
Provides-Extra: dev
License-File: LICENSE
Summary: A Rust implementation of Peter Norvig's spell corrector algorithm for use in Python
Author-email: Ashkan Feyzollahi <ashkanfeyzollahi@gmail.com>
Requires-Python: >=3.8
